{"v":"5.1.16","fr":30,"ip":0,"op":90,"w":440,"h":621,"nm":"doodle-sketch (1)","ddd":0,"assets":[{"id":"image_0","w":440,"h":621,"u":"images/","p":"img_0.png","e":0},{"id":"image_1","w":440,"h":621,"u":"images/","p":"img_1.png","e":0},{"id":"image_2","w":440,"h":621,"u":"images/","p":"img_2.png","e":0},{"id":"image_3","w":440,"h":621,"u":"images/","p":"img_3.png","e":0},{"id":"image_4","w":440,"h":621,"u":"images/","p":"img_4.png","e":0},{"id":"image_5","w":440,"h":621,"u":"images/","p":"img_5.png","e":0},{"id":"image_6","w":440,"h":621,"u":"images/","p":"img_6.png","e":0},{"id":"image_7","w":440,"h":621,"u":"images/","p":"img_7.png","e":0},{"id":"image_8","w":440,"h":621,"u":"images/","p":"img_8.png","e":0},{"id":"image_9","w":440,"h":621,"u":"images/","p":"img_9.png","e":0},{"id":"image_10","w":440,"h":621,"u":"images/","p":"img_10.png","e":0},{"id":"image_11","w":440,"h":621,"u":"images/","p":"img_11.png","e":0},{"id":"image_12","w":440,"h":621,"u":"images/","p":"img_12.png","e":0},{"id":"image_13","w":440,"h":621,"u":"images/","p":"img_13.png","e":0},{"id":"image_14","w":440,"h":621,"u":"images/","p":"img_14.png","e":0},{"id":"image_15","w":73,"h":73,"u":"images/","p":"img_15.png","e":0},{"id":"image_16","w":440,"h":621,"u":"images/","p":"img_16.png","e":0},{"id":"image_17","w":440,"h":621,"u":"images/","p":"img_17.png","e":0},{"id":"image_18","w":440,"h":621,"u":"images/","p":"img_18.png","e":0},{"id":"image_19","w":440,"h":621,"u":"images/","p":"img_19.png","e":0},{"id":"image_20","w":440,"h":621,"u":"images/","p":"img_20.png","e":0},{"id":"image_21","w":440,"h":621,"u":"images/","p":"img_21.png","e":0},{"id":"image_22","w":440,"h":621,"u":"images/","p":"img_22.png","e":0},{"id":"image_23","w":440,"h":621,"u":"images/","p":"img_23.png","e":0},{"id":"image_24","w":440,"h":621,"u":"images/","p":"img_24.png","e":0},{"id":"image_25","w":440,"h":621,"u":"images/","p":"img_25.png","e":0},{"id":"comp_0","layers":[{"ddd":0,"ind":1,"ty":2,"nm":"Rectangle 6 Copy 3","refId":"image_0","sr":1,"ks":{"o":{"a":0,"k":100,"ix":11},"r":{"a":0,"k":0,"ix":10},"p":{"a":0,"k":[220,310.5,0],"ix":2},"a":{"a":0,"k":[220,310.5,0],"ix":1},"s":{"a":0,"k":[100,100,100],"ix":6}},"ao":0,"hasMask":true,"masksProperties":[{"inv":false,"mode":"a","pt":{"a":0,"k":{"i":[[-2.212,0],[0,0],[0,-2.212],[0,0],[2.212,0],[0,0],[0,2.212],[0,0]],"o":[[0,0],[2.212,0],[0,0],[0,2.212],[0,0],[-2.212,0],[0,0],[0,-2.212]],"v":[[202.964,201.667],[235.036,201.667],[239.036,205.667],[239.036,211],[235.036,215],[202.964,215],[198.964,211],[198.964,205.667]],"c":true},"ix":1},"o":{"a":0,"k":100,"ix":3},"x":{"a":0,"k":0,"ix":4},"nm":"Mask 1"}],"ip":0,"op":900,"st":0,"bm":0},{"ddd":0,"ind":2,"ty":2,"nm":"Rectangle 6 Copy 2","refId":"image_1","sr":1,"ks":{"o":{"a":0,"k":100,"ix":11},"r":{"a":0,"k":0,"ix":10},"p":{"a":0,"k":[220,310.5,0],"ix":2},"a":{"a":0,"k":[220,310.5,0],"ix":1},"s":{"a":0,"k":[100,100,100],"ix":6}},"ao":0,"hasMask":true,"masksProperties":[{"inv":false,"mode":"a","pt":{"a":0,"k":{"i":[[-2.212,0],[0,0],[0,-2.212],[0,0],[2.212,0],[0,0],[0,2.212],[0,0]],"o":[[0,0],[2.212,0],[0,0],[0,2.212],[0,0],[-2.212,0],[0,0],[0,-2.212]],"v":[[379.946,201.667],[402,201.667],[406,205.667],[406,211],[402,215],[379.946,215],[375.946,211],[375.946,205.667]],"c":true},"ix":1},"o":{"a":0,"k":100,"ix":3},"x":{"a":0,"k":0,"ix":4},"nm":"Mask 1"}],"ip":0,"op":900,"st":0,"bm":0},{"ddd":0,"ind":3,"ty":2,"nm":"Rectangle 6","refId":"image_2","sr":1,"ks":{"o":{"a":0,"k":100,"ix":11},"r":{"a":0,"k":0,"ix":10},"p":{"a":0,"k":[220,310.5,0],"ix":2},"a":{"a":0,"k":[220,310.5,0],"ix":1},"s":{"a":0,"k":[100,100,100],"ix":6}},"ao":0,"hasMask":true,"masksProperties":[{"inv":false,"mode":"a","pt":{"a":0,"k":{"i":[[-2.212,0],[0,0],[0,-2.212],[0,0],[2.212,0],[0,0],[0,2.212],[0,0]],"o":[[0,0],[2.212,0],[0,0],[0,2.212],[0,0],[-2.212,0],[0,0],[0,-2.212]],"v":[[36,201.667],[58.054,201.667],[62.054,205.667],[62.054,211],[58.054,215],[36,215],[32,211],[32,205.667]],"c":true},"ix":1},"o":{"a":0,"k":100,"ix":3},"x":{"a":0,"k":0,"ix":4},"nm":"Mask 1"}],"ip":0,"op":900,"st":0,"bm":0},{"ddd":0,"ind":4,"ty":2,"nm":"Combined Shape Copy 2","refId":"image_3","sr":1,"ks":{"o":{"a":0,"k":100,"ix":11},"r":{"a":0,"k":0,"ix":10},"p":{"a":0,"k":[220,310.5,0],"ix":2},"a":{"a":0,"k":[220,310.5,0],"ix":1},"s":{"a":0,"k":[100,100,100],"ix":6}},"ao":0,"hasMask":true,"masksProperties":[{"inv":false,"mode":"a","pt":{"a":0,"k":{"i":[[0,-8.284],[0,0],[-8.299,0],[0,0],[0,8.284],[0,0],[8.299,0],[0,0]],"o":[[0,0],[0,8.284],[0,0],[8.299,0],[0,0],[0,-8.284],[0,0],[-8.299,0]],"v":[[55.375,205],[55.375,285],[70.402,300],[190.616,300],[205.643,285],[205.643,205],[190.616,190],[70.402,190]],"c":true},"ix":1},"o":{"a":0,"k":100,"ix":3},"x":{"a":0,"k":0,"ix":4},"nm":"Mask 1"},{"inv":false,"mode":"s","pt":{"a":0,"k":{"i":[[0,0],[0,0],[0,0],[0,0]],"o":[[0,0],[0,0],[0,0],[0,0]],"v":[[68.732,203.333],[192.286,203.333],[192.286,286.667],[68.732,286.667]],"c":true},"ix":1},"o":{"a":0,"k":100,"ix":3},"x":{"a":0,"k":0,"ix":4},"nm":"Mask 2"}],"ip":0,"op":900,"st":0,"bm":0},{"ddd":0,"ind":5,"ty":2,"nm":"Combined Shape","refId":"image_4","sr":1,"ks":{"o":{"a":0,"k":100,"ix":11},"r":{"a":0,"k":0,"ix":10},"p":{"a":0,"k":[220,310.5,0],"ix":2},"a":{"a":0,"k":[220,310.5,0],"ix":1},"s":{"a":0,"k":[100,100,100],"ix":6}},"ao":0,"hasMask":true,"masksProperties":[{"inv":false,"mode":"a","pt":{"a":0,"k":{"i":[[0,-8.284],[0,0],[-8.299,0],[0,0],[0,8.284],[0,0],[8.299,0],[0,0]],"o":[[0,0],[0,8.284],[0,0],[8.299,0],[0,0],[0,-8.284],[0,0],[-8.299,0]],"v":[[232.357,205],[232.357,285],[247.384,300],[367.598,300],[382.625,285],[382.625,205],[367.598,190],[247.384,190]],"c":true},"ix":1},"o":{"a":0,"k":100,"ix":3},"x":{"a":0,"k":0,"ix":4},"nm":"Mask 1"},{"inv":false,"mode":"s","pt":{"a":0,"k":{"i":[[0,0],[0,0],[0,0],[0,0]],"o":[[0,0],[0,0],[0,0],[0,0]],"v":[[245.714,203.333],[369.268,203.333],[369.268,286.667],[245.714,286.667]],"c":true},"ix":1},"o":{"a":0,"k":100,"ix":3},"x":{"a":0,"k":0,"ix":4},"nm":"Mask 2"}],"ip":0,"op":900,"st":0,"bm":0},{"ddd":0,"ind":6,"ty":2,"nm":"Combined Shape Copy","refId":"image_5","sr":1,"ks":{"o":{"a":0,"k":100,"ix":11},"r":{"a":0,"k":0,"ix":10},"p":{"a":1,"k":[{"i":{"x":0.833,"y":0.833},"o":{"x":0.167,"y":0.167},"n":"0p833_0p833_0p167_0p167","t":30,"s":[220,310.5,0],"e":[204.272,298.545,0],"to":[3.79407000541687,-0.04263000190258,0],"ti":[2.6090886592865,-0.02931560389698,0]},{"i":{"x":0.833,"y":0.833},"o":{"x":0.167,"y":0.167},"n":"0p833_0p833_0p167_0p167","t":40,"s":[204.272,298.545,0],"e":[204.272,298.545,0],"to":[-2.03085446357727,0.02281858958304,0],"ti":[2.6090886592865,-0.02931560389698,0]},{"i":{"x":0.833,"y":0.833},"o":{"x":0.167,"y":0.167},"n":"0p833_0p833_0p167_0p167","t":42,"s":[204.272,298.545,0],"e":[220,310.5,0],"to":[-2.03085446357727,0.02281858958304,0],"ti":[-6.49239444732666,0.07294825464487,0]},{"i":{"x":0.833,"y":0.833},"o":{"x":0.167,"y":0.167},"n":"0p833_0p833_0p167_0p167","t":50,"s":[220,310.5,0],"e":[260,310.5,0],"to":[6.74728679656982,-0.07581221312284,0],"ti":[-6.66666650772095,0,0]},{"i":{"x":0.833,"y":0.833},"o":{"x":0.167,"y":0.167},"n":"0p833_0p833_0p167_0p167","t":61,"s":[260,310.5,0],"e":[260,310.5,0],"to":[6.66666650772095,0,0],"ti":[-6.66666650772095,0,0]},{"i":{"x":0.833,"y":0.833},"o":{"x":0.167,"y":0.167},"n":"0p833_0p833_0p167_0p167","t":62,"s":[260,310.5,0],"e":[220,310.5,0],"to":[6.66666650772095,0,0],"ti":[-6.49239444732666,0.07294825464487,0]},{"t":70}],"ix":2},"a":{"a":0,"k":[220,310.5,0],"ix":1},"s":{"a":0,"k":[100,100,100],"ix":6}},"ao":0,"hasMask":true,"masksProperties":[{"inv":false,"mode":"a","pt":{"a":1,"k":[{"i":{"x":0.833,"y":0.833},"o":{"x":0.167,"y":0.167},"n":"0p833_0p833_0p167_0p167","t":30,"s":[{"i":[[0,0],[0,0],[0,0],[0,0],[0,0]],"o":[[0,0],[0,0],[0,0],[0,0],[0,0]],"v":[[84.807,198.333],[122.783,198.333],[69.765,290],[65.393,290],[65.393,231.9]],"c":true}],"e":[{"i":[[0,0],[0,0],[0,0],[0,0],[0,0]],"o":[[0,0],[0,0],[0,0],[0,0],[0,0]],"v":[[89.807,205.333],[120.033,206.333],[74.015,277.25],[75.143,243.25],[74.393,211.4]],"c":true}]},{"i":{"x":0.833,"y":0.833},"o":{"x":0.167,"y":0.167},"n":"0p833_0p833_0p167_0p167","t":40,"s":[{"i":[[0,0],[0,0],[0,0],[0,0],[0,0]],"o":[[0,0],[0,0],[0,0],[0,0],[0,0]],"v":[[89.807,205.333],[120.033,206.333],[74.015,277.25],[75.143,243.25],[74.393,211.4]],"c":true}],"e":[{"i":[[0,0],[0,0],[0,0],[0,0],[0,0]],"o":[[0,0],[0,0],[0,0],[0,0],[0,0]],"v":[[89.807,205.333],[120.033,206.333],[74.015,277.25],[75.143,243.25],[74.393,211.4]],"c":true}]},{"i":{"x":0.833,"y":0.833},"o":{"x":0.167,"y":0.167},"n":"0p833_0p833_0p167_0p167","t":42,"s":[{"i":[[0,0],[0,0],[0,0],[0,0],[0,0]],"o":[[0,0],[0,0],[0,0],[0,0],[0,0]],"v":[[89.807,205.333],[120.033,206.333],[74.015,277.25],[75.143,243.25],[74.393,211.4]],"c":true}],"e":[{"i":[[0,0],[0,0],[0,0],[0,0],[0,0]],"o":[[0,0],[0,0],[0,0],[0,0],[0,0]],"v":[[84.807,198.333],[122.783,198.333],[69.765,290],[65.393,290],[65.393,231.9]],"c":true}]},{"i":{"x":0.833,"y":0.833},"o":{"x":0.167,"y":0.167},"n":"0p833_0p833_0p167_0p167","t":50,"s":[{"i":[[0,0],[0,0],[0,0],[0,0],[0,0]],"o":[[0,0],[0,0],[0,0],[0,0],[0,0]],"v":[[84.807,198.333],[122.783,198.333],[69.765,290],[65.393,290],[65.393,231.9]],"c":true}],"e":[{"i":[[0,0],[0,0],[0,0],[0,0],[0,0]],"o":[[0,0],[0,0],[0,0],[0,0],[0,0]],"v":[[84.807,198.333],[122.783,198.333],[69.765,290],[45.393,290.25],[45.768,264.275]],"c":true}]},{"i":{"x":0.833,"y":0.833},"o":{"x":0.167,"y":0.167},"n":"0p833_0p833_0p167_0p167","t":56,"s":[{"i":[[0,0],[0,0],[0,0],[0,0],[0,0]],"o":[[0,0],[0,0],[0,0],[0,0],[0,0]],"v":[[84.807,198.333],[122.783,198.333],[69.765,290],[45.393,290.25],[45.768,264.275]],"c":true}],"e":[{"i":[[0,0],[0,0],[0,0],[0,0],[0,0]],"o":[[0,0],[0,0],[0,0],[0,0],[0,0]],"v":[[84.807,198.333],[122.783,198.333],[69.765,290],[33.893,290.1],[33.993,279.799]],"c":true}]},{"i":{"x":0.833,"y":0.833},"o":{"x":0.167,"y":0.167},"n":"0p833_0p833_0p167_0p167","t":59,"s":[{"i":[[0,0],[0,0],[0,0],[0,0],[0,0]],"o":[[0,0],[0,0],[0,0],[0,0],[0,0]],"v":[[84.807,198.333],[122.783,198.333],[69.765,290],[33.893,290.1],[33.993,279.799]],"c":true}],"e":[{"i":[[0,0],[0,0],[0,0],[0,0],[0,0]],"o":[[0,0],[0,0],[0,0],[0,0],[0,0]],"v":[[84.807,198.333],[122.783,198.333],[69.765,290],[47.893,290.25],[26.143,290.15]],"c":true}]},{"i":{"x":0.833,"y":0.833},"o":{"x":0.167,"y":0.167},"n":"0p833_0p833_0p167_0p167","t":61,"s":[{"i":[[0,0],[0,0],[0,0],[0,0],[0,0]],"o":[[0,0],[0,0],[0,0],[0,0],[0,0]],"v":[[84.807,198.333],[122.783,198.333],[69.765,290],[47.893,290.25],[26.143,290.15]],"c":true}],"e":[{"i":[[0,0],[0,0],[0,0],[0,0],[0,0]],"o":[[0,0],[0,0],[0,0],[0,0],[0,0]],"v":[[84.807,198.333],[122.783,198.333],[69.765,290],[33.893,290.1],[33.993,279.799]],"c":true}]},{"i":{"x":0.833,"y":0.833},"o":{"x":0.167,"y":0.167},"n":"0p833_0p833_0p167_0p167","t":63,"s":[{"i":[[0,0],[0,0],[0,0],[0,0],[0,0]],"o":[[0,0],[0,0],[0,0],[0,0],[0,0]],"v":[[84.807,198.333],[122.783,198.333],[69.765,290],[33.893,290.1],[33.993,279.799]],"c":true}],"e":[{"i":[[0,0],[0,0],[0,0],[0,0],[0,0]],"o":[[0,0],[0,0],[0,0],[0,0],[0,0]],"v":[[84.807,198.333],[122.783,198.333],[69.765,290],[45.393,290.25],[45.768,264.275]],"c":true}]},{"i":{"x":0.833,"y":0.833},"o":{"x":0.167,"y":0.167},"n":"0p833_0p833_0p167_0p167","t":66,"s":[{"i":[[0,0],[0,0],[0,0],[0,0],[0,0]],"o":[[0,0],[0,0],[0,0],[0,0],[0,0]],"v":[[84.807,198.333],[122.783,198.333],[69.765,290],[45.393,290.25],[45.768,264.275]],"c":true}],"e":[{"i":[[0,0],[0,0],[0,0],[0,0],[0,0]],"o":[[0,0],[0,0],[0,0],[0,0],[0,0]],"v":[[84.807,198.333],[122.783,198.333],[69.765,290],[65.393,290],[65.393,231.9]],"c":true}]},{"t":70}],"ix":1},"o":{"a":0,"k":100,"ix":3},"x":{"a":0,"k":0,"ix":4},"nm":"Mask 1"}],"ip":0,"op":900,"st":0,"bm":0},{"ddd":0,"ind":7,"ty":2,"nm":"Combined Shape","refId":"image_6","sr":1,"ks":{"o":{"a":0,"k":100,"ix":11},"r":{"a":0,"k":0,"ix":10},"p":{"a":1,"k":[{"i":{"x":0.833,"y":0.833},"o":{"x":0.167,"y":0.167},"n":"0p833_0p833_0p167_0p167","t":30,"s":[220,310.5,0],"e":[204.75,293.75,0],"to":[0,0,0],"ti":[0,0,0]},{"i":{"x":0.833,"y":0.833},"o":{"x":0.167,"y":0.167},"n":"0p833_0p833_0p167_0p167","t":40,"s":[204.75,293.75,0],"e":[204.75,293.75,0],"to":[0,0,0],"ti":[0,0,0]},{"i":{"x":0.833,"y":0.833},"o":{"x":0.167,"y":0.167},"n":"0p833_0p833_0p167_0p167","t":42,"s":[204.75,293.75,0],"e":[220,310.5,0],"to":[0,0,0],"ti":[0,0,0]},{"i":{"x":0.833,"y":0.833},"o":{"x":0.167,"y":0.167},"n":"0p833_0p833_0p167_0p167","t":50,"s":[220,310.5,0],"e":[260,310.5,0],"to":[0,0,0],"ti":[0,0,0]},{"i":{"x":0.833,"y":0.833},"o":{"x":0.167,"y":0.167},"n":"0p833_0p833_0p167_0p167","t":61,"s":[260,310.5,0],"e":[260,310.5,0],"to":[0,0,0],"ti":[0,0,0]},{"i":{"x":0.833,"y":0.833},"o":{"x":0.167,"y":0.167},"n":"0p833_0p833_0p167_0p167","t":62,"s":[260,310.5,0],"e":[220,310.5,0],"to":[0,0,0],"ti":[0,0,0]},{"t":70}],"ix":2},"a":{"a":0,"k":[220,310.5,0],"ix":1},"s":{"a":0,"k":[100,100,100],"ix":6}},"ao":0,"hasMask":true,"masksProperties":[{"inv":false,"mode":"a","pt":{"a":1,"k":[{"i":{"x":0.833,"y":0.833},"o":{"x":0.167,"y":0.167},"n":"0p833_0p833_0p167_0p167","t":30,"s":[{"i":[[0,0],[0,0],[0,0],[0,0],[0,0]],"o":[[0,0],[0,0],[0,0],[0,0],[0,0]],"v":[[261.789,198.333],[299.765,198.333],[246.747,290],[242.375,290],[242.375,231.9]],"c":true}],"e":[{"i":[[0,0],[0,0],[0,0],[0,0],[0,0]],"o":[[0,0],[0,0],[0,0],[0,0],[0,0]],"v":[[262.039,212.333],[292.015,211.833],[250.997,283],[253.375,258.75],[251.125,229.65]],"c":true}]},{"i":{"x":0.833,"y":0.833},"o":{"x":0.167,"y":0.167},"n":"0p833_0p833_0p167_0p167","t":40,"s":[{"i":[[0,0],[0,0],[0,0],[0,0],[0,0]],"o":[[0,0],[0,0],[0,0],[0,0],[0,0]],"v":[[262.039,212.333],[292.015,211.833],[250.997,283],[253.375,258.75],[251.125,229.65]],"c":true}],"e":[{"i":[[0,0],[0,0],[0,0],[0,0],[0,0]],"o":[[0,0],[0,0],[0,0],[0,0],[0,0]],"v":[[262.039,212.333],[292.015,211.833],[250.997,283],[253.375,258.75],[251.125,229.65]],"c":true}]},{"i":{"x":0.833,"y":0.833},"o":{"x":0.167,"y":0.167},"n":"0p833_0p833_0p167_0p167","t":42,"s":[{"i":[[0,0],[0,0],[0,0],[0,0],[0,0]],"o":[[0,0],[0,0],[0,0],[0,0],[0,0]],"v":[[262.039,212.333],[292.015,211.833],[250.997,283],[253.375,258.75],[251.125,229.65]],"c":true}],"e":[{"i":[[0,0],[0,0],[0,0],[0,0],[0,0]],"o":[[0,0],[0,0],[0,0],[0,0],[0,0]],"v":[[261.789,198.333],[299.765,198.333],[246.747,290],[242.375,290],[242.375,231.9]],"c":true}]},{"i":{"x":0.833,"y":0.833},"o":{"x":0.167,"y":0.167},"n":"0p833_0p833_0p167_0p167","t":50,"s":[{"i":[[0,0],[0,0],[0,0],[0,0],[0,0]],"o":[[0,0],[0,0],[0,0],[0,0],[0,0]],"v":[[261.789,198.333],[299.765,198.333],[246.747,290],[242.375,290],[242.375,231.9]],"c":true}],"e":[{"i":[[0,0],[0,0],[0,0],[0,0],[0,0]],"o":[[0,0],[0,0],[0,0],[0,0],[0,0]],"v":[[261.789,198.333],[299.765,198.333],[246.747,290],[222.125,289.75],[223,262.275]],"c":true}]},{"i":{"x":0.833,"y":0.833},"o":{"x":0.167,"y":0.167},"n":"0p833_0p833_0p167_0p167","t":56,"s":[{"i":[[0,0],[0,0],[0,0],[0,0],[0,0]],"o":[[0,0],[0,0],[0,0],[0,0],[0,0]],"v":[[261.789,198.333],[299.765,198.333],[246.747,290],[222.125,289.75],[223,262.275]],"c":true}],"e":[{"i":[[0,0],[0,0],[0,0],[0,0],[0,0]],"o":[[0,0],[0,0],[0,0],[0,0],[0,0]],"v":[[261.789,198.333],[299.765,198.333],[246.747,290],[211.775,290.15],[211.375,279.3]],"c":true}]},{"i":{"x":0.833,"y":0.833},"o":{"x":0.167,"y":0.167},"n":"0p833_0p833_0p167_0p167","t":59,"s":[{"i":[[0,0],[0,0],[0,0],[0,0],[0,0]],"o":[[0,0],[0,0],[0,0],[0,0],[0,0]],"v":[[261.789,198.333],[299.765,198.333],[246.747,290],[211.775,290.15],[211.375,279.3]],"c":true}],"e":[{"i":[[0,0],[0,0],[0,0],[0,0],[0,0]],"o":[[0,0],[0,0],[0,0],[0,0],[0,0]],"v":[[261.789,198.333],[299.765,198.333],[246.747,290],[225.625,290.25],[203.625,290.65]],"c":true}]},{"i":{"x":0.833,"y":0.833},"o":{"x":0.167,"y":0.167},"n":"0p833_0p833_0p167_0p167","t":61,"s":[{"i":[[0,0],[0,0],[0,0],[0,0],[0,0]],"o":[[0,0],[0,0],[0,0],[0,0],[0,0]],"v":[[261.789,198.333],[299.765,198.333],[246.747,290],[225.625,290.25],[203.625,290.65]],"c":true}],"e":[{"i":[[0,0],[0,0],[0,0],[0,0],[0,0]],"o":[[0,0],[0,0],[0,0],[0,0],[0,0]],"v":[[261.789,198.333],[299.765,198.333],[246.747,290],[211.775,290.15],[211.375,279.3]],"c":true}]},{"i":{"x":0.833,"y":0.833},"o":{"x":0.167,"y":0.167},"n":"0p833_0p833_0p167_0p167","t":63,"s":[{"i":[[0,0],[0,0],[0,0],[0,0],[0,0]],"o":[[0,0],[0,0],[0,0],[0,0],[0,0]],"v":[[261.789,198.333],[299.765,198.333],[246.747,290],[211.775,290.15],[211.375,279.3]],"c":true}],"e":[{"i":[[0,0],[0,0],[0,0],[0,0],[0,0]],"o":[[0,0],[0,0],[0,0],[0,0],[0,0]],"v":[[261.789,198.333],[299.765,198.333],[246.747,290],[222.125,289.75],[223,262.275]],"c":true}]},{"i":{"x":0.833,"y":0.833},"o":{"x":0.167,"y":0.167},"n":"0p833_0p833_0p167_0p167","t":66,"s":[{"i":[[0,0],[0,0],[0,0],[0,0],[0,0]],"o":[[0,0],[0,0],[0,0],[0,0],[0,0]],"v":[[261.789,198.333],[299.765,198.333],[246.747,290],[222.125,289.75],[223,262.275]],"c":true}],"e":[{"i":[[0,0],[0,0],[0,0],[0,0],[0,0]],"o":[[0,0],[0,0],[0,0],[0,0],[0,0]],"v":[[261.789,198.333],[299.765,198.333],[246.747,290],[242.375,290],[242.375,231.9]],"c":true}]},{"t":70}],"ix":1},"o":{"a":0,"k":100,"ix":3},"x":{"a":0,"k":0,"ix":4},"nm":"Mask 1"}],"ip":0,"op":900,"st":0,"bm":0}]},{"id":"comp_1","layers":[{"ddd":0,"ind":1,"ty":0,"nm":"Mask by Combined Shape","refId":"comp_2","sr":1,"ks":{"o":{"a":0,"k":100,"ix":11},"r":{"a":0,"k":0,"ix":10},"p":{"a":0,"k":[220,310.5,0],"ix":2},"a":{"a":0,"k":[220,310.5,0],"ix":1},"s":{"a":0,"k":[100,100,100],"ix":6}},"ao":0,"hasMask":true,"masksProperties":[{"inv":false,"mode":"a","pt":{"a":0,"k":{"i":[[0,29.367],[-27.614,0],[0,-29.368],[27.614,0]],"o":[[0,-29.368],[27.614,0],[0,29.367],[-27.614,0]],"v":[[171,385.825],[221,332.651],[271,385.825],[221,439]],"c":true},"ix":1},"o":{"a":0,"k":100,"ix":3},"x":{"a":0,"k":0,"ix":4},"nm":"Mask 1"},{"inv":false,"mode":"s","pt":{"a":0,"k":{"i":[[0,0],[0,0],[0,0],[0,0]],"o":[[0,0],[0,0],[0,0],[0,0]],"v":[[130,324.143],[320,324.143],[320,372],[130,372]],"c":true},"ix":1},"o":{"a":0,"k":100,"ix":3},"x":{"a":0,"k":0,"ix":4},"nm":"Mask 2"}],"w":440,"h":621,"ip":0,"op":900,"st":0,"bm":0},{"ddd":0,"ind":2,"ty":2,"nm":"Combined Shape","refId":"image_9","sr":1,"ks":{"o":{"a":0,"k":100,"ix":11},"r":{"a":0,"k":0,"ix":10},"p":{"a":0,"k":[220,310.5,0],"ix":2},"a":{"a":0,"k":[220,310.5,0],"ix":1},"s":{"a":0,"k":[100,100,100],"ix":6}},"ao":0,"hasMask":true,"masksProperties":[{"inv":false,"mode":"a","pt":{"a":0,"k":{"i":[[0,29.367],[-27.614,0],[0,-29.368],[27.614,0]],"o":[[0,-29.368],[27.614,0],[0,29.367],[-27.614,0]],"v":[[171,385.825],[221,332.651],[271,385.825],[221,439]],"c":true},"ix":1},"o":{"a":0,"k":100,"ix":3},"x":{"a":0,"k":0,"ix":4},"nm":"Mask 1"},{"inv":false,"mode":"s","pt":{"a":0,"k":{"i":[[0,0],[0,0],[0,0],[0,0]],"o":[[0,0],[0,0],[0,0],[0,0]],"v":[[130,324.143],[320,324.143],[320,372],[130,372]],"c":true},"ix":1},"o":{"a":0,"k":100,"ix":3},"x":{"a":0,"k":0,"ix":4},"nm":"Mask 2"}],"ip":0,"op":900,"st":0,"bm":0}]},{"id":"comp_2","layers":[{"ddd":0,"ind":1,"ty":2,"nm":"Rectangle 7","refId":"image_7","sr":1,"ks":{"o":{"a":0,"k":100,"ix":11},"r":{"a":0,"k":0,"ix":10},"p":{"a":0,"k":[220,310.5,0],"ix":2},"a":{"a":0,"k":[220,310.5,0],"ix":1},"s":{"a":0,"k":[100,100,100],"ix":6}},"ao":0,"hasMask":true,"masksProperties":[{"inv":false,"mode":"a","pt":{"a":0,"k":{"i":[[0,0],[0,0],[0,0],[0,0]],"o":[[0,0],[0,0],[0,0],[0,0]],"v":[[145.074,340.471],[298.778,340.471],[298.778,385.794],[145.074,385.794]],"c":true},"ix":1},"o":{"a":0,"k":100,"ix":3},"x":{"a":0,"k":0,"ix":4},"nm":"Mask 1"}],"ip":0,"op":900,"st":0,"bm":0},{"ddd":0,"ind":2,"ty":2,"nm":"Oval 2","refId":"image_8","sr":1,"ks":{"o":{"a":0,"k":100,"ix":11},"r":{"a":0,"k":0,"ix":10},"p":{"a":0,"k":[220,310.5,0],"ix":2},"a":{"a":0,"k":[220,310.5,0],"ix":1},"s":{"a":0,"k":[100,100,100],"ix":6}},"ao":0,"hasMask":true,"masksProperties":[{"inv":false,"mode":"a","pt":{"a":0,"k":{"i":[[0,24.895],[-24.772,0],[0,-24.895],[24.772,0]],"o":[[0,-24.895],[24.772,0],[0,24.895],[-24.772,0]],"v":[[176,450.577],[220.853,405.5],[265.706,450.577],[220.853,495.654]],"c":true},"ix":1},"o":{"a":0,"k":100,"ix":3},"x":{"a":0,"k":0,"ix":4},"nm":"Mask 1"}],"ip":0,"op":900,"st":0,"bm":0}]},{"id":"comp_3","layers":[{"ddd":0,"ind":1,"ty":2,"nm":"Rectangle 5 Copy","refId":"image_10","sr":1,"ks":{"o":{"a":0,"k":100,"ix":11},"r":{"a":1,"k":[{"i":{"x":[0.833],"y":[0.833]},"o":{"x":[0.167],"y":[0.167]},"n":["0p833_0p833_0p167_0p167"],"t":50,"s":[0],"e":[-5.645]},{"i":{"x":[0.833],"y":[0.833]},"o":{"x":[0.167],"y":[0.167]},"n":["0p833_0p833_0p167_0p167"],"t":60,"s":[-5.645],"e":[0]},{"t":70}],"ix":10},"p":{"a":1,"k":[{"i":{"x":0.833,"y":0.833},"o":{"x":0.167,"y":0.167},"n":"0p833_0p833_0p167_0p167","t":50,"s":[220,310.5,0],"e":[229,303.5,0],"to":[1.5,-1.16666662693024,0],"ti":[0,0,0]},{"i":{"x":0.833,"y":0.833},"o":{"x":0.167,"y":0.167},"n":"0p833_0p833_0p167_0p167","t":60,"s":[229,303.5,0],"e":[220,310.5,0],"to":[0,0,0],"ti":[1.5,-1.16666662693024,0]},{"t":70}],"ix":2},"a":{"a":0,"k":[220,310.5,0],"ix":1},"s":{"a":0,"k":[100,100,100],"ix":6}},"ao":0,"hasMask":true,"masksProperties":[{"inv":false,"mode":"a","pt":{"a":0,"k":{"i":[[0,-7.732],[-7.767,0],[0,0],[0,7.732],[7.767,0],[0,0]],"o":[[0,7.732],[0,0],[7.767,0],[0,-7.732],[0,0],[-7.767,0]],"v":[[88,181],[102.064,195],[164.936,195],[179,181],[164.936,167],[102.064,167]],"c":true},"ix":1},"o":{"a":0,"k":100,"ix":3},"x":{"a":0,"k":0,"ix":4},"nm":"Mask 1"}],"ip":0,"op":900,"st":0,"bm":0},{"ddd":0,"ind":2,"ty":2,"nm":"Rectangle 5","refId":"image_11","sr":1,"ks":{"o":{"a":0,"k":100,"ix":11},"r":{"a":1,"k":[{"i":{"x":[0.833],"y":[0.833]},"o":{"x":[0.167],"y":[0.167]},"n":["0p833_0p833_0p167_0p167"],"t":50,"s":[0],"e":[12.039]},{"i":{"x":[0.833],"y":[0.833]},"o":{"x":[0.167],"y":[0.167]},"n":["0p833_0p833_0p167_0p167"],"t":60,"s":[12.039],"e":[0]},{"t":70}],"ix":10},"p":{"a":1,"k":[{"i":{"x":0.833,"y":0.833},"o":{"x":0.167,"y":0.167},"n":"0p833_0p833_0p167_0p167","t":50,"s":[220,310.5,0],"e":[198,290.5,0],"to":[-3.66666674613953,-3.33333325386047,0],"ti":[0,0,0]},{"i":{"x":0.833,"y":0.833},"o":{"x":0.167,"y":0.167},"n":"0p833_0p833_0p167_0p167","t":60,"s":[198,290.5,0],"e":[220,310.5,0],"to":[0,0,0],"ti":[-3.66666674613953,-3.33333325386047,0]},{"t":70}],"ix":2},"a":{"a":0,"k":[220,310.5,0],"ix":1},"s":{"a":0,"k":[100,100,100],"ix":6}},"ao":0,"hasMask":true,"masksProperties":[{"inv":false,"mode":"a","pt":{"a":0,"k":{"i":[[0,-7.732],[-7.767,0],[0,0],[0,7.732],[7.767,0],[0,0]],"o":[[0,7.732],[0,0],[7.767,0],[0,-7.732],[0,0],[-7.767,0]],"v":[[261,181],[275.064,195],[337.936,195],[352,181],[337.936,167],[275.064,167]],"c":true},"ix":1},"o":{"a":0,"k":100,"ix":3},"x":{"a":0,"k":0,"ix":4},"nm":"Mask 1"}],"ip":0,"op":900,"st":0,"bm":0}]},{"id":"comp_4","layers":[{"ddd":0,"ind":1,"ty":2,"nm":"Oval Copy","refId":"image_12","sr":1,"ks":{"o":{"a":0,"k":100,"ix":11},"r":{"a":0,"k":0,"ix":10},"p":{"a":0,"k":[220,310.5,0],"ix":2},"a":{"a":0,"k":[220,310.5,0],"ix":1},"s":{"a":0,"k":[100,100,100],"ix":6}},"ao":0,"hasMask":true,"masksProperties":[{"inv":false,"mode":"a","pt":{"a":1,"k":[{"i":{"x":0.833,"y":0.833},"o":{"x":0.167,"y":0.167},"n":"0p833_0p833_0p167_0p167","t":30,"s":[{"i":[[0,11.874],[-11.874,0],[0,-11.874],[11.874,0]],"o":[[0,-11.874],[11.874,0],[0,11.874],[-11.874,0]],"v":[[110,230.5],[131.5,209],[153,230.5],[131.5,252]],"c":true}],"e":[{"i":[[0,11.874],[-11.874,0],[0,-11.874],[11.874,0]],"o":[[0,-11.874],[11.874,0],[0,11.874],[-11.874,0]],"v":[[110,230.5],[131.5,212.5],[153,230.5],[131.5,247.5]],"c":true}]},{"i":{"x":0.833,"y":0.833},"o":{"x":0.167,"y":0.167},"n":"0p833_0p833_0p167_0p167","t":40,"s":[{"i":[[0,11.874],[-11.874,0],[0,-11.874],[11.874,0]],"o":[[0,-11.874],[11.874,0],[0,11.874],[-11.874,0]],"v":[[110,230.5],[131.5,212.5],[153,230.5],[131.5,247.5]],"c":true}],"e":[{"i":[[0,11.874],[-11.874,0],[0,-11.874],[11.874,0]],"o":[[0,-11.874],[11.874,0],[0,11.874],[-11.874,0]],"v":[[110,230.5],[131.5,209],[153,230.5],[131.5,252]],"c":true}]},{"i":{"x":0.833,"y":0.833},"o":{"x":0.167,"y":0.167},"n":"0p833_0p833_0p167_0p167","t":50,"s":[{"i":[[0,11.874],[-11.874,0],[0,-11.874],[11.874,0]],"o":[[0,-11.874],[11.874,0],[0,11.874],[-11.874,0]],"v":[[110,230.5],[131.5,209],[153,230.5],[131.5,252]],"c":true}],"e":[{"i":[[0,11.874],[-11.874,0],[0,-11.874],[11.874,0]],"o":[[0,-11.874],[11.874,0],[0,11.874],[-11.874,0]],"v":[[110,230.5],[131.5,212.5],[153,230.5],[131.5,247.5]],"c":true}]},{"i":{"x":0.833,"y":0.833},"o":{"x":0.167,"y":0.167},"n":"0p833_0p833_0p167_0p167","t":60,"s":[{"i":[[0,11.874],[-11.874,0],[0,-11.874],[11.874,0]],"o":[[0,-11.874],[11.874,0],[0,11.874],[-11.874,0]],"v":[[110,230.5],[131.5,212.5],[153,230.5],[131.5,247.5]],"c":true}],"e":[{"i":[[0,11.874],[-11.874,0],[0,-11.874],[11.874,0]],"o":[[0,-11.874],[11.874,0],[0,11.874],[-11.874,0]],"v":[[110,230.5],[131.5,209],[153,230.5],[131.5,252]],"c":true}]},{"t":70}],"ix":1},"o":{"a":0,"k":100,"ix":3},"x":{"a":0,"k":0,"ix":4},"nm":"Mask 1"}],"ip":0,"op":900,"st":0,"bm":0},{"ddd":0,"ind":2,"ty":2,"nm":"Oval","refId":"image_13","sr":1,"ks":{"o":{"a":0,"k":100,"ix":11},"r":{"a":0,"k":0,"ix":10},"p":{"a":0,"k":[220,310.5,0],"ix":2},"a":{"a":0,"k":[220,310.5,0],"ix":1},"s":{"a":0,"k":[100,100,100],"ix":6}},"ao":0,"hasMask":true,"masksProperties":[{"inv":false,"mode":"a","pt":{"a":1,"k":[{"i":{"x":0.833,"y":0.833},"o":{"x":0.167,"y":0.167},"n":"0p833_0p833_0p167_0p167","t":30,"s":[{"i":[[0,11.874],[-11.874,0],[0,-11.874],[11.874,0]],"o":[[0,-11.874],[11.874,0],[0,11.874],[-11.874,0]],"v":[[284,230.5],[305.5,209],[327,230.5],[305.5,252]],"c":true}],"e":[{"i":[[0,11.874],[-11.874,0],[0,-11.874],[11.874,0]],"o":[[0,-11.874],[11.874,0],[0,11.874],[-11.874,0]],"v":[[284,230.5],[305,212.5],[327,230.5],[305.5,247.5]],"c":true}]},{"i":{"x":0.833,"y":0.833},"o":{"x":0.167,"y":0.167},"n":"0p833_0p833_0p167_0p167","t":40,"s":[{"i":[[0,11.874],[-11.874,0],[0,-11.874],[11.874,0]],"o":[[0,-11.874],[11.874,0],[0,11.874],[-11.874,0]],"v":[[284,230.5],[305,212.5],[327,230.5],[305.5,247.5]],"c":true}],"e":[{"i":[[0,11.874],[-11.874,0],[0,-11.874],[11.874,0]],"o":[[0,-11.874],[11.874,0],[0,11.874],[-11.874,0]],"v":[[284,230.5],[305.5,209],[327,230.5],[305.5,252]],"c":true}]},{"i":{"x":0.833,"y":0.833},"o":{"x":0.167,"y":0.167},"n":"0p833_0p833_0p167_0p167","t":50,"s":[{"i":[[0,11.874],[-11.874,0],[0,-11.874],[11.874,0]],"o":[[0,-11.874],[11.874,0],[0,11.874],[-11.874,0]],"v":[[284,230.5],[305.5,209],[327,230.5],[305.5,252]],"c":true}],"e":[{"i":[[0,11.874],[-11.874,0],[0,-11.874],[11.874,0]],"o":[[0,-11.874],[11.874,0],[0,11.874],[-11.874,0]],"v":[[284,230.5],[305,212.5],[327,230.5],[305.5,247.5]],"c":true}]},{"i":{"x":0.833,"y":0.833},"o":{"x":0.167,"y":0.167},"n":"0p833_0p833_0p167_0p167","t":60,"s":[{"i":[[0,11.874],[-11.874,0],[0,-11.874],[11.874,0]],"o":[[0,-11.874],[11.874,0],[0,11.874],[-11.874,0]],"v":[[284,230.5],[305,212.5],[327,230.5],[305.5,247.5]],"c":true}],"e":[{"i":[[0,11.874],[-11.874,0],[0,-11.874],[11.874,0]],"o":[[0,-11.874],[11.874,0],[0,11.874],[-11.874,0]],"v":[[284,230.5],[305.5,209],[327,230.5],[305.5,252]],"c":true}]},{"t":71}],"ix":1},"o":{"a":0,"k":100,"ix":3},"x":{"a":0,"k":0,"ix":4},"nm":"Mask 1"}],"ip":0,"op":900,"st":0,"bm":0}]},{"id":"comp_5","layers":[{"ddd":0,"ind":1,"ty":0,"nm":"Group 2 Copy","refId":"comp_6","sr":1,"ks":{"o":{"a":0,"k":100,"ix":11},"r":{"a":0,"k":0,"ix":10},"p":{"a":0,"k":[220,310.5,0],"ix":2},"a":{"a":0,"k":[220,310.5,0],"ix":1},"s":{"a":0,"k":[100,100,100],"ix":6}},"ao":0,"w":440,"h":621,"ip":0,"op":900,"st":0,"bm":0},{"ddd":0,"ind":2,"ty":0,"nm":"Group 2","refId":"comp_7","sr":1,"ks":{"o":{"a":0,"k":100,"ix":11},"r":{"a":0,"k":0,"ix":10},"p":{"a":0,"k":[220,310.5,0],"ix":2},"a":{"a":0,"k":[220,310.5,0],"ix":1},"s":{"a":0,"k":[100,100,100],"ix":6}},"ao":0,"w":440,"h":621,"ip":0,"op":900,"st":0,"bm":0}]},{"id":"comp_6","layers":[{"ddd":0,"ind":1,"ty":2,"nm":"Oval 3","refId":"image_20","sr":1,"ks":{"o":{"a":0,"k":100,"ix":11},"r":{"a":0,"k":0,"ix":10},"p":{"a":0,"k":[220,310.5,0],"ix":2},"a":{"a":0,"k":[220,310.5,0],"ix":1},"s":{"a":0,"k":[100,100,100],"ix":6}},"ao":0,"hasMask":true,"masksProperties":[{"inv":false,"mode":"a","pt":{"a":0,"k":{"i":[[0,11.874],[-11.874,0],[0,-11.874],[11.874,0]],"o":[[0,-11.874],[11.874,0],[0,11.874],[-11.874,0]],"v":[[21,254.5],[42.5,233],[64,254.5],[42.5,276]],"c":true},"ix":1},"o":{"a":0,"k":100,"ix":3},"x":{"a":0,"k":0,"ix":4},"nm":"Mask 1"}],"ip":0,"op":900,"st":0,"bm":0},{"ddd":0,"ind":2,"ty":2,"nm":"Oval 3","refId":"image_21","sr":1,"ks":{"o":{"a":0,"k":100,"ix":11},"r":{"a":0,"k":0,"ix":10},"p":{"a":0,"k":[220,310.5,0],"ix":2},"a":{"a":0,"k":[220,310.5,0],"ix":1},"s":{"a":0,"k":[100,100,100],"ix":6}},"ao":0,"hasMask":true,"masksProperties":[{"inv":false,"mode":"a","pt":{"a":0,"k":{"i":[[0,23.472],[-23.472,0],[0,-23.472],[23.472,0]],"o":[[0,-23.472],[23.472,0],[0,23.472],[-23.472,0]],"v":[[0,254.5],[42.5,212],[85,254.5],[42.5,297]],"c":true},"ix":1},"o":{"a":0,"k":100,"ix":3},"x":{"a":0,"k":0,"ix":4},"nm":"Mask 1"}],"ip":0,"op":900,"st":0,"bm":0}]},{"id":"comp_7","layers":[{"ddd":0,"ind":1,"ty":2,"nm":"Oval 3","refId":"image_22","sr":1,"ks":{"o":{"a":0,"k":100,"ix":11},"r":{"a":0,"k":0,"ix":10},"p":{"a":0,"k":[220,310.5,0],"ix":2},"a":{"a":0,"k":[220,310.5,0],"ix":1},"s":{"a":0,"k":[100,100,100],"ix":6}},"ao":0,"hasMask":true,"masksProperties":[{"inv":false,"mode":"a","pt":{"a":0,"k":{"i":[[0,11.874],[-11.874,0],[0,-11.874],[11.874,0]],"o":[[0,-11.874],[11.874,0],[0,11.874],[-11.874,0]],"v":[[376,254.5],[397.5,233],[419,254.5],[397.5,276]],"c":true},"ix":1},"o":{"a":0,"k":100,"ix":3},"x":{"a":0,"k":0,"ix":4},"nm":"Mask 1"}],"ip":0,"op":900,"st":0,"bm":0},{"ddd":0,"ind":2,"ty":2,"nm":"Oval 3","refId":"image_23","sr":1,"ks":{"o":{"a":0,"k":100,"ix":11},"r":{"a":0,"k":0,"ix":10},"p":{"a":0,"k":[220,310.5,0],"ix":2},"a":{"a":0,"k":[220,310.5,0],"ix":1},"s":{"a":0,"k":[100,100,100],"ix":6}},"ao":0,"hasMask":true,"masksProperties":[{"inv":false,"mode":"a","pt":{"a":0,"k":{"i":[[0,23.472],[-23.472,0],[0,-23.472],[23.472,0]],"o":[[0,-23.472],[23.472,0],[0,23.472],[-23.472,0]],"v":[[355,254.5],[397.5,212],[440,254.5],[397.5,297]],"c":true},"ix":1},"o":{"a":0,"k":100,"ix":3},"x":{"a":0,"k":0,"ix":4},"nm":"Mask 1"}],"ip":0,"op":900,"st":0,"bm":0}]}],"layers":[{"ddd":0,"ind":1,"ty":0,"nm":"Glasses","refId":"comp_0","sr":1,"ks":{"o":{"a":0,"k":100,"ix":11},"r":{"a":1,"k":[{"i":{"x":[0.667],"y":[1]},"o":{"x":[0.333],"y":[0]},"n":["0p667_1_0p333_0"],"t":30,"s":[0],"e":[6.537]},{"i":{"x":[0.667],"y":[1]},"o":{"x":[0.333],"y":[0]},"n":["0p667_1_0p333_0"],"t":40,"s":[6.537],"e":[6.537]},{"i":{"x":[0.833],"y":[1]},"o":{"x":[0.333],"y":[0]},"n":["0p833_1_0p333_0"],"t":42,"s":[6.537],"e":[0]},{"i":{"x":[0.706],"y":[0.999]},"o":{"x":[0.357],"y":[-0.006]},"n":["0p706_0p999_0p357_-0p006"],"t":50,"s":[0],"e":[-15.033]},{"i":{"x":[0.793],"y":[1]},"o":{"x":[0.437],"y":[-0.001]},"n":["0p793_1_0p437_-0p001"],"t":62,"s":[-15.033],"e":[0]},{"t":70}],"ix":10},"p":{"a":1,"k":[{"i":{"x":0.667,"y":1},"o":{"x":0.333,"y":0},"n":"0p667_1_0p333_0","t":30,"s":[220,310.5,0],"e":[234,309.5,0],"to":[2.33333325386047,-0.16666667163372,0],"ti":[-2.33333325386047,0.16666667163372,0]},{"i":{"x":0.667,"y":0.667},"o":{"x":0.333,"y":0.333},"n":"0p667_0p667_0p333_0p333","t":40,"s":[234,309.5,0],"e":[234,309.5,0],"to":[0,0,0],"ti":[0,0,0]},{"i":{"x":0.667,"y":1},"o":{"x":0.333,"y":0},"n":"0p667_1_0p333_0","t":42,"s":[234,309.5,0],"e":[220,310.5,0],"to":[-2.33333325386047,0.16666667163372,0],"ti":[4.5,0,0]},{"i":{"x":0.585,"y":0.939},"o":{"x":0.179,"y":0},"n":"0p585_0p939_0p179_0","t":50,"s":[220,310.5,0],"e":[201.267,296.5,0],"to":[-2.84290194511414,0,0],"ti":[-0.61165332794189,0,0]},{"i":{"x":0.701,"y":1},"o":{"x":0.348,"y":0.034},"n":"0p701_1_0p348_0p034","t":62,"s":[201.267,296.5,0],"e":[220,310.5,0],"to":[0.24624961614609,0,0],"ti":[1.29166507720947,0,0]},{"t":70}],"ix":2},"a":{"a":0,"k":[220,310.5,0],"ix":1},"s":{"a":0,"k":[77.456,77.456,100],"ix":6}},"ao":0,"w":440,"h":621,"ip":0,"op":900,"st":0,"bm":0},{"ddd":0,"ind":2,"ty":0,"nm":"Mouth","refId":"comp_1","sr":1,"ks":{"o":{"a":0,"k":100,"ix":11},"r":{"a":1,"k":[{"i":{"x":[0.833],"y":[1]},"o":{"x":[0.333],"y":[0]},"n":["0p833_1_0p333_0"],"t":30,"s":[0],"e":[6.527]},{"i":{"x":[0.833],"y":[1]},"o":{"x":[0.167],"y":[0]},"n":["0p833_1_0p167_0"],"t":40,"s":[6.527],"e":[6.527]},{"i":{"x":[0.667],"y":[1]},"o":{"x":[0.167],"y":[0]},"n":["0p667_1_0p167_0"],"t":42,"s":[6.527],"e":[0]},{"i":{"x":[0.833],"y":[1]},"o":{"x":[0.333],"y":[0]},"n":["0p833_1_0p333_0"],"t":50,"s":[0],"e":[-9.789]},{"i":{"x":[0.833],"y":[1]},"o":{"x":[0.167],"y":[0]},"n":["0p833_1_0p167_0"],"t":60,"s":[-9.789],"e":[-9.789]},{"i":{"x":[0.667],"y":[1]},"o":{"x":[0.167],"y":[0]},"n":["0p667_1_0p167_0"],"t":62,"s":[-9.789],"e":[0]},{"t":70}],"ix":10},"p":{"a":1,"k":[{"i":{"x":0.667,"y":1},"o":{"x":0.333,"y":0},"n":"0p667_1_0p333_0","t":30,"s":[220,310.5,0],"e":[235,295.5,0],"to":[2.5,-2.5,0],"ti":[-2.5,2.5,0]},{"i":{"x":0.667,"y":0.667},"o":{"x":0.333,"y":0.333},"n":"0p667_0p667_0p333_0p333","t":40,"s":[235,295.5,0],"e":[235,295.5,0],"to":[0,0,0],"ti":[0,0,0]},{"i":{"x":0.667,"y":1},"o":{"x":0.333,"y":0},"n":"0p667_1_0p333_0","t":42,"s":[235,295.5,0],"e":[220,310.5,0],"to":[-2.5,2.5,0],"ti":[5.83333349227905,-3.83333325386047,0]},{"i":{"x":0.667,"y":1},"o":{"x":0.333,"y":0},"n":"0p667_1_0p333_0","t":50,"s":[220,310.5,0],"e":[200,318.5,0],"to":[-5.83333349227905,3.83333325386047,0],"ti":[3.33333325386047,-1.33333337306976,0]},{"i":{"x":0.667,"y":0.667},"o":{"x":0.333,"y":0.333},"n":"0p667_0p667_0p333_0p333","t":60,"s":[200,318.5,0],"e":[200,318.5,0],"to":[0,0,0],"ti":[0,0,0]},{"i":{"x":0.667,"y":1},"o":{"x":0.333,"y":0},"n":"0p667_1_0p333_0","t":62,"s":[200,318.5,0],"e":[220,310.5,0],"to":[3.33333325386047,-1.33333337306976,0],"ti":[-3.33333325386047,1.33333337306976,0]},{"t":70}],"ix":2},"a":{"a":0,"k":[220,310.5,0],"ix":1},"s":{"a":1,"k":[{"i":{"x":[0.667,0.667,0.667],"y":[1,1,-4.636]},"o":{"x":[0.333,0.333,0.333],"y":[0,0,0]},"n":["0p667_1_0p333_0","0p667_1_0p333_0","0p667_-4p636_0p333_0"],"t":30,"s":[77.456,77.456,100],"e":[77.456,94.151,100]},{"i":{"x":[0.667,0.667,0.667],"y":[1,1,1]},"o":{"x":[0.333,0.333,0.333],"y":[0,0,1.127]},"n":["0p667_1_0p333_0","0p667_1_0p333_0","0p667_1_0p333_1p127"],"t":40,"s":[77.456,94.151,100],"e":[77.456,94.151,100]},{"i":{"x":[0.667,0.667,0.667],"y":[1,1,1]},"o":{"x":[0.333,0.333,0.333],"y":[0,0,0]},"n":["0p667_1_0p333_0","0p667_1_0p333_0","0p667_1_0p333_0"],"t":42,"s":[77.456,94.151,100],"e":[77.456,77.456,100]},{"i":{"x":[0.667,0.667,0.667],"y":[1,1,1]},"o":{"x":[0.333,0.333,0.333],"y":[0,0,0]},"n":["0p667_1_0p333_0","0p667_1_0p333_0","0p667_1_0p333_0"],"t":50,"s":[77.456,77.456,100],"e":[77.456,66.26,100]},{"i":{"x":[0.667,0.667,0.667],"y":[1,1,1]},"o":{"x":[0.333,0.333,0.333],"y":[0,0,0]},"n":["0p667_1_0p333_0","0p667_1_0p333_0","0p667_1_0p333_0"],"t":60,"s":[77.456,66.26,100],"e":[77.456,66.26,100]},{"i":{"x":[0.667,0.667,0.667],"y":[1,1,1]},"o":{"x":[0.333,0.333,0.333],"y":[0,0,0]},"n":["0p667_1_0p333_0","0p667_1_0p333_0","0p667_1_0p333_0"],"t":62,"s":[77.456,66.26,100],"e":[77.456,77.456,100]},{"t":70}],"ix":6}},"ao":0,"w":440,"h":621,"ip":0,"op":900,"st":0,"bm":0},{"ddd":0,"ind":3,"ty":0,"nm":"Eyebrows","refId":"comp_3","sr":1,"ks":{"o":{"a":0,"k":100,"ix":11},"r":{"a":1,"k":[{"i":{"x":[0.833],"y":[1]},"o":{"x":[0.333],"y":[0]},"n":["0p833_1_0p333_0"],"t":30,"s":[0],"e":[6.527]},{"i":{"x":[0.833],"y":[1]},"o":{"x":[0.167],"y":[0]},"n":["0p833_1_0p167_0"],"t":40,"s":[6.527],"e":[6.527]},{"i":{"x":[0.667],"y":[1]},"o":{"x":[0.167],"y":[0]},"n":["0p667_1_0p167_0"],"t":42,"s":[6.527],"e":[0]},{"i":{"x":[0.833],"y":[1]},"o":{"x":[0.333],"y":[0]},"n":["0p833_1_0p333_0"],"t":50,"s":[0],"e":[-9.789]},{"i":{"x":[0.833],"y":[1]},"o":{"x":[0.167],"y":[0]},"n":["0p833_1_0p167_0"],"t":60,"s":[-9.789],"e":[-9.789]},{"i":{"x":[0.667],"y":[1]},"o":{"x":[0.167],"y":[0]},"n":["0p667_1_0p167_0"],"t":62,"s":[-9.789],"e":[0]},{"t":70}],"ix":10},"p":{"a":1,"k":[{"i":{"x":0.667,"y":1},"o":{"x":0.333,"y":0},"n":"0p667_1_0p333_0","t":30,"s":[220,310.5,0],"e":[233,300.5,0],"to":[2.16666674613953,-1.66666662693024,0],"ti":[-2.16666674613953,1.66666662693024,0]},{"i":{"x":0.667,"y":0.667},"o":{"x":0.333,"y":0.333},"n":"0p667_0p667_0p333_0p333","t":40,"s":[233,300.5,0],"e":[233,300.5,0],"to":[0,0,0],"ti":[0,0,0]},{"i":{"x":0.667,"y":1},"o":{"x":0.333,"y":0},"n":"0p667_1_0p333_0","t":42,"s":[233,300.5,0],"e":[220,310.5,0],"to":[-2.16666674613953,1.66666662693024,0],"ti":[6.66666650772095,-0.66666668653488,0]},{"i":{"x":0.667,"y":1},"o":{"x":0.333,"y":0},"n":"0p667_1_0p333_0","t":50,"s":[220,310.5,0],"e":[193,304.5,0],"to":[-6.66666650772095,0.66666668653488,0],"ti":[4.5,1,0]},{"i":{"x":0.667,"y":0.667},"o":{"x":0.333,"y":0.333},"n":"0p667_0p667_0p333_0p333","t":60,"s":[193,304.5,0],"e":[193,304.5,0],"to":[0,0,0],"ti":[0,0,0]},{"i":{"x":0.667,"y":1},"o":{"x":0.333,"y":0},"n":"0p667_1_0p333_0","t":62,"s":[193,304.5,0],"e":[220,310.5,0],"to":[4.5,1,0],"ti":[-4.5,-1,0]},{"t":70}],"ix":2},"a":{"a":0,"k":[220,310.5,0],"ix":1},"s":{"a":1,"k":[{"i":{"x":[0.667,0.667,0.667],"y":[1,1,1]},"o":{"x":[0.333,0.333,0.333],"y":[0,0,0]},"n":["0p667_1_0p333_0","0p667_1_0p333_0","0p667_1_0p333_0"],"t":30,"s":[77.456,77.456,100],"e":[77.456,77.456,100]},{"i":{"x":[0.667,0.667,0.667],"y":[1,1,1]},"o":{"x":[0.333,0.333,0.333],"y":[0,0,0]},"n":["0p667_1_0p333_0","0p667_1_0p333_0","0p667_1_0p333_0"],"t":50,"s":[77.456,77.456,100],"e":[77.456,77.456,100]},{"t":70}],"ix":6}},"ao":0,"w":440,"h":621,"ip":0,"op":900,"st":0,"bm":0},{"ddd":0,"ind":4,"ty":0,"nm":"Eyes","refId":"comp_4","sr":1,"ks":{"o":{"a":0,"k":100,"ix":11},"r":{"a":1,"k":[{"i":{"x":[0.833],"y":[1]},"o":{"x":[0.333],"y":[0]},"n":["0p833_1_0p333_0"],"t":30,"s":[0],"e":[6.527]},{"i":{"x":[0.833],"y":[1]},"o":{"x":[0.167],"y":[0]},"n":["0p833_1_0p167_0"],"t":40,"s":[6.527],"e":[6.527]},{"i":{"x":[0.667],"y":[1]},"o":{"x":[0.167],"y":[0]},"n":["0p667_1_0p167_0"],"t":42,"s":[6.527],"e":[0]},{"i":{"x":[0.833],"y":[1]},"o":{"x":[0.333],"y":[0]},"n":["0p833_1_0p333_0"],"t":50,"s":[0],"e":[-9.789]},{"i":{"x":[0.833],"y":[1]},"o":{"x":[0.167],"y":[0]},"n":["0p833_1_0p167_0"],"t":60,"s":[-9.789],"e":[-9.789]},{"i":{"x":[0.667],"y":[1]},"o":{"x":[0.167],"y":[0]},"n":["0p667_1_0p167_0"],"t":62,"s":[-9.789],"e":[0]},{"t":70}],"ix":10},"p":{"a":1,"k":[{"i":{"x":0.667,"y":1},"o":{"x":0.333,"y":0},"n":"0p667_1_0p333_0","t":30,"s":[220,310.5,0],"e":[233,313.5,0],"to":[2.16666674613953,0.5,0],"ti":[-2.16666674613953,-0.5,0]},{"i":{"x":0.667,"y":0.667},"o":{"x":0.333,"y":0.333},"n":"0p667_0p667_0p333_0p333","t":40,"s":[233,313.5,0],"e":[233,313.5,0],"to":[0,0,0],"ti":[0,0,0]},{"i":{"x":0.667,"y":1},"o":{"x":0.333,"y":0},"n":"0p667_1_0p333_0","t":42,"s":[233,313.5,0],"e":[220,310.5,0],"to":[-2.16666674613953,-0.5,0],"ti":[5.66666650772095,-0.16666667163372,0]},{"i":{"x":0.667,"y":1},"o":{"x":0.333,"y":0},"n":"0p667_1_0p333_0","t":50,"s":[220,310.5,0],"e":[199,314.5,0],"to":[-5.66666650772095,0.16666667163372,0],"ti":[3.5,-0.66666668653488,0]},{"i":{"x":0.667,"y":0.667},"o":{"x":0.333,"y":0.333},"n":"0p667_0p667_0p333_0p333","t":60,"s":[199,314.5,0],"e":[199,314.5,0],"to":[0,0,0],"ti":[0,0,0]},{"i":{"x":0.667,"y":1},"o":{"x":0.333,"y":0},"n":"0p667_1_0p333_0","t":62,"s":[199,314.5,0],"e":[220,310.5,0],"to":[3.5,-0.66666668653488,0],"ti":[-3.5,0.66666668653488,0]},{"t":70}],"ix":2},"a":{"a":0,"k":[220,310.5,0],"ix":1},"s":{"a":1,"k":[{"i":{"x":[0.667,0.667,0.667],"y":[1,1,1]},"o":{"x":[0.333,0.333,0.333],"y":[0,0,0]},"n":["0p667_1_0p333_0","0p667_1_0p333_0","0p667_1_0p333_0"],"t":30,"s":[77.456,77.456,100],"e":[77.456,77.456,100]},{"i":{"x":[0.667,0.667,0.667],"y":[1,1,1]},"o":{"x":[0.333,0.333,0.333],"y":[0,0,0]},"n":["0p667_1_0p333_0","0p667_1_0p333_0","0p667_1_0p333_0"],"t":50,"s":[77.456,77.456,100],"e":[77.456,77.456,100]},{"t":70}],"ix":6}},"ao":0,"w":440,"h":621,"ip":0,"op":900,"st":0,"bm":0},{"ddd":0,"ind":5,"ty":2,"nm":"Hair","refId":"image_14","sr":1,"ks":{"o":{"a":0,"k":100,"ix":11},"r":{"a":1,"k":[{"i":{"x":[0.833],"y":[1]},"o":{"x":[0.333],"y":[0]},"n":["0p833_1_0p333_0"],"t":30,"s":[0],"e":[6.527]},{"i":{"x":[0.833],"y":[1]},"o":{"x":[0.167],"y":[0]},"n":["0p833_1_0p167_0"],"t":40,"s":[6.527],"e":[6.527]},{"i":{"x":[0.667],"y":[1]},"o":{"x":[0.167],"y":[0]},"n":["0p667_1_0p167_0"],"t":42,"s":[6.527],"e":[0]},{"i":{"x":[0.833],"y":[1]},"o":{"x":[0.333],"y":[0]},"n":["0p833_1_0p333_0"],"t":50,"s":[0],"e":[-9.789]},{"i":{"x":[0.833],"y":[1]},"o":{"x":[0.167],"y":[0]},"n":["0p833_1_0p167_0"],"t":60,"s":[-9.789],"e":[-9.789]},{"i":{"x":[0.667],"y":[1]},"o":{"x":[0.167],"y":[0]},"n":["0p667_1_0p167_0"],"t":62,"s":[-9.789],"e":[0]},{"t":70}],"ix":10},"p":{"a":1,"k":[{"i":{"x":0.667,"y":1},"o":{"x":0.333,"y":0},"n":"0p667_1_0p333_0","t":30,"s":[220,310.5,0],"e":[233,313.5,0],"to":[2.16666674613953,0.5,0],"ti":[-2.16666674613953,-0.5,0]},{"i":{"x":0.667,"y":0.667},"o":{"x":0.333,"y":0.333},"n":"0p667_0p667_0p333_0p333","t":40,"s":[233,313.5,0],"e":[233,313.5,0],"to":[0,0,0],"ti":[0,0,0]},{"i":{"x":0.667,"y":1},"o":{"x":0.333,"y":0},"n":"0p667_1_0p333_0","t":42,"s":[233,313.5,0],"e":[220,310.5,0],"to":[-2.16666674613953,-0.5,0],"ti":[5.66666650772095,-0.16666667163372,0]},{"i":{"x":0.667,"y":1},"o":{"x":0.333,"y":0},"n":"0p667_1_0p333_0","t":50,"s":[220,310.5,0],"e":[199,314.5,0],"to":[-5.66666650772095,0.16666667163372,0],"ti":[3.5,-0.66666668653488,0]},{"i":{"x":0.667,"y":0.667},"o":{"x":0.333,"y":0.333},"n":"0p667_0p667_0p333_0p333","t":60,"s":[199,314.5,0],"e":[199,314.5,0],"to":[0,0,0],"ti":[0,0,0]},{"i":{"x":0.667,"y":1},"o":{"x":0.333,"y":0},"n":"0p667_1_0p333_0","t":62,"s":[199,314.5,0],"e":[220,310.5,0],"to":[3.5,-0.66666668653488,0],"ti":[-3.5,0.66666668653488,0]},{"t":70}],"ix":2},"a":{"a":0,"k":[220,310.5,0],"ix":1},"s":{"a":1,"k":[{"i":{"x":[0.667,0.667,0.667],"y":[1,1,1]},"o":{"x":[0.333,0.333,0.333],"y":[0,0,0]},"n":["0p667_1_0p333_0","0p667_1_0p333_0","0p667_1_0p333_0"],"t":30,"s":[77.456,77.456,100],"e":[77.456,77.456,100]},{"i":{"x":[0.667,0.667,0.667],"y":[1,1,1]},"o":{"x":[0.333,0.333,0.333],"y":[0,0,0]},"n":["0p667_1_0p333_0","0p667_1_0p333_0","0p667_1_0p333_0"],"t":50,"s":[77.456,77.456,100],"e":[77.456,77.456,100]},{"t":70}],"ix":6}},"ao":0,"hasMask":true,"masksProperties":[{"inv":false,"mode":"a","pt":{"a":0,"k":{"i":[[6.102,-8.87],[0,0],[0,-7.101],[-19.296,0],[0,0],[-1.882,17.814],[0,0],[0.116,1.93],[19.262,-1.16],[0,0]],"o":[[0,0],[-4.021,5.846],[0,19.341],[0,0],[17.872,0],[0,0],[0.203,-1.923],[-1.157,-19.306],[0,0],[-10.73,0.646]],"v":[[154.938,26.846],[114.175,86.1],[108,105.98],[142.939,141],[370.562,141],[405.307,109.668],[412.806,38.71],[412.937,32.921],[375.965,0.064],[181.606,11.769]],"c":true},"ix":1},"o":{"a":0,"k":100,"ix":3},"x":{"a":0,"k":0,"ix":4},"nm":"Mask 1"}],"ip":0,"op":90,"st":0,"bm":0},{"ddd":0,"ind":6,"ty":2,"nm":"Nose","refId":"image_15","sr":1,"ks":{"o":{"a":0,"k":100,"ix":11},"r":{"a":1,"k":[{"i":{"x":[0.833],"y":[1]},"o":{"x":[0.333],"y":[0]},"n":["0p833_1_0p333_0"],"t":30,"s":[0],"e":[6.527]},{"i":{"x":[0.833],"y":[1]},"o":{"x":[0.167],"y":[0]},"n":["0p833_1_0p167_0"],"t":40,"s":[6.527],"e":[6.527]},{"i":{"x":[0.667],"y":[1]},"o":{"x":[0.167],"y":[0]},"n":["0p667_1_0p167_0"],"t":42,"s":[6.527],"e":[0]},{"i":{"x":[0.833],"y":[1]},"o":{"x":[0.333],"y":[0]},"n":["0p833_1_0p333_0"],"t":50,"s":[0],"e":[-9.789]},{"i":{"x":[0.833],"y":[1]},"o":{"x":[0.167],"y":[0]},"n":["0p833_1_0p167_0"],"t":60,"s":[-9.789],"e":[-9.789]},{"i":{"x":[0.667],"y":[1]},"o":{"x":[0.167],"y":[0]},"n":["0p667_1_0p167_0"],"t":62,"s":[-9.789],"e":[0]},{"t":70}],"ix":10},"p":{"a":1,"k":[{"i":{"x":0.667,"y":1},"o":{"x":0.333,"y":0},"n":"0p667_1_0p333_0","t":30,"s":[219.5,281.5,0],"e":[232.5,284.5,0],"to":[2.16666674613953,0.5,0],"ti":[-2.16666674613953,-0.5,0]},{"i":{"x":0.667,"y":0.667},"o":{"x":0.333,"y":0.333},"n":"0p667_0p667_0p333_0p333","t":40,"s":[232.5,284.5,0],"e":[232.5,284.5,0],"to":[0,0,0],"ti":[0,0,0]},{"i":{"x":0.667,"y":1},"o":{"x":0.333,"y":0},"n":"0p667_1_0p333_0","t":42,"s":[232.5,284.5,0],"e":[219.5,281.5,0],"to":[-2.16666674613953,-0.5,0],"ti":[5.66666650772095,-0.16666667163372,0]},{"i":{"x":0.667,"y":1},"o":{"x":0.333,"y":0},"n":"0p667_1_0p333_0","t":50,"s":[219.5,281.5,0],"e":[198.5,285.5,0],"to":[-5.66666650772095,0.16666667163372,0],"ti":[3.5,-0.66666668653488,0]},{"i":{"x":0.667,"y":0.667},"o":{"x":0.333,"y":0.333},"n":"0p667_0p667_0p333_0p333","t":60,"s":[198.5,285.5,0],"e":[198.5,285.5,0],"to":[0,0,0],"ti":[0,0,0]},{"i":{"x":0.667,"y":1},"o":{"x":0.333,"y":0},"n":"0p667_1_0p333_0","t":62,"s":[198.5,285.5,0],"e":[219.5,281.5,0],"to":[3.5,-0.66666668653488,0],"ti":[-3.5,0.66666668653488,0]},{"t":70}],"ix":2},"a":{"a":0,"k":[36.5,28.5,0],"ix":1},"s":{"a":1,"k":[{"i":{"x":[0.667,0.667,0.667],"y":[1,1,1]},"o":{"x":[0.333,0.333,0.333],"y":[0,0,0]},"n":["0p667_1_0p333_0","0p667_1_0p333_0","0p667_1_0p333_0"],"t":30,"s":[77.456,77.456,100],"e":[77.456,77.456,100]},{"i":{"x":[0.667,0.667,0.667],"y":[1,1,1]},"o":{"x":[0.333,0.333,0.333],"y":[0,0,0]},"n":["0p667_1_0p333_0","0p667_1_0p333_0","0p667_1_0p333_0"],"t":50,"s":[77.456,77.456,100],"e":[77.456,77.456,100]},{"t":70}],"ix":6}},"ao":0,"hasMask":true,"masksProperties":[{"inv":false,"mode":"n","pt":{"a":0,"k":{"i":[[0,0],[0,0],[0,0]],"o":[[0,0],[0,0],[0,0]],"v":[[36.5,7],[68,70],[5,70]],"c":true},"ix":1},"o":{"a":0,"k":100,"ix":3},"x":{"a":0,"k":0,"ix":4},"nm":"Mask 1"}],"ip":0,"op":90,"st":0,"bm":0},{"ddd":0,"ind":7,"ty":2,"nm":"Mouth Skin","refId":"image_16","sr":1,"ks":{"o":{"a":0,"k":100,"ix":11},"r":{"a":1,"k":[{"i":{"x":[0.833],"y":[1]},"o":{"x":[0.333],"y":[0]},"n":["0p833_1_0p333_0"],"t":30,"s":[0],"e":[6.527]},{"i":{"x":[0.833],"y":[1]},"o":{"x":[0.167],"y":[0]},"n":["0p833_1_0p167_0"],"t":40,"s":[6.527],"e":[6.527]},{"i":{"x":[0.667],"y":[1]},"o":{"x":[0.167],"y":[0]},"n":["0p667_1_0p167_0"],"t":42,"s":[6.527],"e":[0]},{"i":{"x":[0.833],"y":[1]},"o":{"x":[0.333],"y":[0]},"n":["0p833_1_0p333_0"],"t":50,"s":[0],"e":[-9.789]},{"i":{"x":[0.833],"y":[1]},"o":{"x":[0.167],"y":[0]},"n":["0p833_1_0p167_0"],"t":60,"s":[-9.789],"e":[-9.789]},{"i":{"x":[0.667],"y":[1]},"o":{"x":[0.167],"y":[0]},"n":["0p667_1_0p167_0"],"t":62,"s":[-9.789],"e":[0]},{"t":70}],"ix":10},"p":{"a":1,"k":[{"i":{"x":0.667,"y":1},"o":{"x":0.333,"y":0},"n":"0p667_1_0p333_0","t":30,"s":[220,310.5,0],"e":[233,313.5,0],"to":[2.16666674613953,0.5,0],"ti":[-2.16666674613953,-0.5,0]},{"i":{"x":0.667,"y":0.667},"o":{"x":0.333,"y":0.333},"n":"0p667_0p667_0p333_0p333","t":40,"s":[233,313.5,0],"e":[233,313.5,0],"to":[0,0,0],"ti":[0,0,0]},{"i":{"x":0.667,"y":1},"o":{"x":0.333,"y":0},"n":"0p667_1_0p333_0","t":42,"s":[233,313.5,0],"e":[220,310.5,0],"to":[-2.16666674613953,-0.5,0],"ti":[5.66666650772095,-0.16666667163372,0]},{"i":{"x":0.667,"y":1},"o":{"x":0.333,"y":0},"n":"0p667_1_0p333_0","t":50,"s":[220,310.5,0],"e":[199,314.5,0],"to":[-5.66666650772095,0.16666667163372,0],"ti":[3.5,-0.66666668653488,0]},{"i":{"x":0.667,"y":0.667},"o":{"x":0.333,"y":0.333},"n":"0p667_0p667_0p333_0p333","t":60,"s":[199,314.5,0],"e":[199,314.5,0],"to":[0,0,0],"ti":[0,0,0]},{"i":{"x":0.667,"y":1},"o":{"x":0.333,"y":0},"n":"0p667_1_0p333_0","t":62,"s":[199,314.5,0],"e":[220,310.5,0],"to":[3.5,-0.66666668653488,0],"ti":[-3.5,0.66666668653488,0]},{"t":70}],"ix":2},"a":{"a":0,"k":[220,310.5,0],"ix":1},"s":{"a":1,"k":[{"i":{"x":[0.667,0.667,0.667],"y":[1,1,1]},"o":{"x":[0.333,0.333,0.333],"y":[0,0,0]},"n":["0p667_1_0p333_0","0p667_1_0p333_0","0p667_1_0p333_0"],"t":30,"s":[77.456,77.456,100],"e":[77.456,77.456,100]},{"i":{"x":[0.667,0.667,0.667],"y":[1,1,1]},"o":{"x":[0.333,0.333,0.333],"y":[0,0,0]},"n":["0p667_1_0p333_0","0p667_1_0p333_0","0p667_1_0p333_0"],"t":50,"s":[77.456,77.456,100],"e":[77.456,77.456,100]},{"t":70}],"ix":6}},"ao":0,"hasMask":true,"masksProperties":[{"inv":false,"mode":"a","pt":{"a":0,"k":{"i":[[0,-28.364],[0,0],[-28.535,0],[0,0],[0,28.364],[0,0],[28.535,0],[0,0]],"o":[[0,0],[0,28.364],[0,0],[28.535,0],[0,0],[0,-28.364],[0,0],[-28.535,0]],"v":[[142,397.358],[142,405.642],[193.667,457],[245.333,457],[297,405.642],[297,397.358],[245.333,346],[193.667,346]],"c":true},"ix":1},"o":{"a":0,"k":100,"ix":3},"x":{"a":0,"k":0,"ix":4},"nm":"Mask 1"}],"ip":0,"op":90,"st":0,"bm":0},{"ddd":0,"ind":8,"ty":2,"nm":"Mustache","refId":"image_17","sr":1,"ks":{"o":{"a":0,"k":100,"ix":11},"r":{"a":1,"k":[{"i":{"x":[0.833],"y":[1]},"o":{"x":[0.333],"y":[0]},"n":["0p833_1_0p333_0"],"t":30,"s":[0],"e":[6.527]},{"i":{"x":[0.833],"y":[1]},"o":{"x":[0.167],"y":[0]},"n":["0p833_1_0p167_0"],"t":40,"s":[6.527],"e":[6.527]},{"i":{"x":[0.667],"y":[1]},"o":{"x":[0.167],"y":[0]},"n":["0p667_1_0p167_0"],"t":42,"s":[6.527],"e":[0]},{"i":{"x":[0.833],"y":[1]},"o":{"x":[0.333],"y":[0]},"n":["0p833_1_0p333_0"],"t":50,"s":[0],"e":[-9.789]},{"i":{"x":[0.833],"y":[1]},"o":{"x":[0.167],"y":[0]},"n":["0p833_1_0p167_0"],"t":60,"s":[-9.789],"e":[-9.789]},{"i":{"x":[0.667],"y":[1]},"o":{"x":[0.167],"y":[0]},"n":["0p667_1_0p167_0"],"t":62,"s":[-9.789],"e":[0]},{"t":70}],"ix":10},"p":{"a":1,"k":[{"i":{"x":0.667,"y":1},"o":{"x":0.333,"y":0},"n":"0p667_1_0p333_0","t":30,"s":[220,310.5,0],"e":[233,313.5,0],"to":[2.16666674613953,0.5,0],"ti":[-2.16666674613953,-0.5,0]},{"i":{"x":0.667,"y":0.667},"o":{"x":0.333,"y":0.333},"n":"0p667_0p667_0p333_0p333","t":40,"s":[233,313.5,0],"e":[233,313.5,0],"to":[0,0,0],"ti":[0,0,0]},{"i":{"x":0.667,"y":1},"o":{"x":0.333,"y":0},"n":"0p667_1_0p333_0","t":42,"s":[233,313.5,0],"e":[220,310.5,0],"to":[-2.16666674613953,-0.5,0],"ti":[5.66666650772095,-0.16666667163372,0]},{"i":{"x":0.667,"y":1},"o":{"x":0.333,"y":0},"n":"0p667_1_0p333_0","t":50,"s":[220,310.5,0],"e":[199,314.5,0],"to":[-5.66666650772095,0.16666667163372,0],"ti":[3.5,-0.66666668653488,0]},{"i":{"x":0.667,"y":0.667},"o":{"x":0.333,"y":0.333},"n":"0p667_0p667_0p333_0p333","t":60,"s":[199,314.5,0],"e":[199,314.5,0],"to":[0,0,0],"ti":[0,0,0]},{"i":{"x":0.667,"y":1},"o":{"x":0.333,"y":0},"n":"0p667_1_0p333_0","t":62,"s":[199,314.5,0],"e":[220,310.5,0],"to":[3.5,-0.66666668653488,0],"ti":[-3.5,0.66666668653488,0]},{"t":70}],"ix":2},"a":{"a":0,"k":[220,310.5,0],"ix":1},"s":{"a":1,"k":[{"i":{"x":[0.667,0.667,0.667],"y":[1,1,1]},"o":{"x":[0.333,0.333,0.333],"y":[0,0,0]},"n":["0p667_1_0p333_0","0p667_1_0p333_0","0p667_1_0p333_0"],"t":30,"s":[77.456,77.456,100],"e":[77.456,77.456,100]},{"i":{"x":[0.667,0.667,0.667],"y":[1,1,1]},"o":{"x":[0.333,0.333,0.333],"y":[0,0,0]},"n":["0p667_1_0p333_0","0p667_1_0p333_0","0p667_1_0p333_0"],"t":50,"s":[77.456,77.456,100],"e":[77.456,77.456,100]},{"t":70}],"ix":6}},"ao":0,"hasMask":true,"masksProperties":[{"inv":false,"mode":"a","pt":{"a":0,"k":{"i":[[0,-28.594],[0,0],[-28.535,0],[0,0],[0,28.594],[0,0],[28.535,0],[0,0]],"o":[[0,0],[0,28.594],[0,0],[28.535,0],[0,0],[0,-28.594],[0,0],[-28.535,0]],"v":[[108,371.773],[108,430.227],[159.667,482],[281.333,482],[333,430.227],[333,371.773],[281.333,320],[159.667,320]],"c":true},"ix":1},"o":{"a":0,"k":100,"ix":3},"x":{"a":0,"k":0,"ix":4},"nm":"Mask 1"}],"ip":0,"op":90,"st":0,"bm":0},{"ddd":0,"ind":9,"ty":2,"nm":"Face","refId":"image_18","sr":1,"ks":{"o":{"a":0,"k":100,"ix":11},"r":{"a":1,"k":[{"i":{"x":[0.833],"y":[1]},"o":{"x":[0.333],"y":[0]},"n":["0p833_1_0p333_0"],"t":30,"s":[0],"e":[6.527]},{"i":{"x":[0.833],"y":[1]},"o":{"x":[0.167],"y":[0]},"n":["0p833_1_0p167_0"],"t":40,"s":[6.527],"e":[6.527]},{"i":{"x":[0.667],"y":[1]},"o":{"x":[0.167],"y":[0]},"n":["0p667_1_0p167_0"],"t":42,"s":[6.527],"e":[0]},{"i":{"x":[0.833],"y":[1]},"o":{"x":[0.333],"y":[0]},"n":["0p833_1_0p333_0"],"t":50,"s":[0],"e":[-9.789]},{"i":{"x":[0.833],"y":[1]},"o":{"x":[0.167],"y":[0]},"n":["0p833_1_0p167_0"],"t":60,"s":[-9.789],"e":[-9.789]},{"i":{"x":[0.667],"y":[1]},"o":{"x":[0.167],"y":[0]},"n":["0p667_1_0p167_0"],"t":62,"s":[-9.789],"e":[0]},{"t":70}],"ix":10},"p":{"a":1,"k":[{"i":{"x":0.667,"y":1},"o":{"x":0.333,"y":0},"n":"0p667_1_0p333_0","t":30,"s":[220,310.5,0],"e":[233,313.5,0],"to":[2.16666674613953,0.5,0],"ti":[-2.16666674613953,-0.5,0]},{"i":{"x":0.667,"y":0.667},"o":{"x":0.333,"y":0.333},"n":"0p667_0p667_0p333_0p333","t":40,"s":[233,313.5,0],"e":[233,313.5,0],"to":[0,0,0],"ti":[0,0,0]},{"i":{"x":0.667,"y":1},"o":{"x":0.333,"y":0},"n":"0p667_1_0p333_0","t":42,"s":[233,313.5,0],"e":[220,310.5,0],"to":[-2.16666674613953,-0.5,0],"ti":[5.66666650772095,-0.16666667163372,0]},{"i":{"x":0.667,"y":1},"o":{"x":0.333,"y":0},"n":"0p667_1_0p333_0","t":50,"s":[220,310.5,0],"e":[199,314.5,0],"to":[-5.66666650772095,0.16666667163372,0],"ti":[3.5,-0.66666668653488,0]},{"i":{"x":0.667,"y":0.667},"o":{"x":0.333,"y":0.333},"n":"0p667_0p667_0p333_0p333","t":60,"s":[199,314.5,0],"e":[199,314.5,0],"to":[0,0,0],"ti":[0,0,0]},{"i":{"x":0.667,"y":1},"o":{"x":0.333,"y":0},"n":"0p667_1_0p333_0","t":62,"s":[199,314.5,0],"e":[220,310.5,0],"to":[3.5,-0.66666668653488,0],"ti":[-3.5,0.66666668653488,0]},{"t":70}],"ix":2},"a":{"a":0,"k":[220,310.5,0],"ix":1},"s":{"a":1,"k":[{"i":{"x":[0.667,0.667,0.667],"y":[1,1,1]},"o":{"x":[0.333,0.333,0.333],"y":[0,0,0]},"n":["0p667_1_0p333_0","0p667_1_0p333_0","0p667_1_0p333_0"],"t":30,"s":[77.456,77.456,100],"e":[77.456,77.456,100]},{"i":{"x":[0.667,0.667,0.667],"y":[1,1,1]},"o":{"x":[0.333,0.333,0.333],"y":[0,0,0]},"n":["0p667_1_0p333_0","0p667_1_0p333_0","0p667_1_0p333_0"],"t":50,"s":[77.456,77.456,100],"e":[77.456,77.456,100]},{"t":70}],"ix":6}},"ao":0,"hasMask":true,"masksProperties":[{"inv":false,"mode":"a","pt":{"a":0,"k":{"i":[[0,0],[0,0],[0,-3.383],[0,0],[-46.898,0],[0,0],[0,46.944],[0,0],[0.384,3.28]],"o":[[0,0],[-0.384,3.28],[0,0],[0,46.944],[0,0],[46.898,0],[0,0],[0,-3.383],[0,0]],"v":[[388.419,141],[51.581,141],[51,151],[51,316],[135.916,401],[304.084,401],[389,316],[389,151],[388.419,141]],"c":true},"ix":1},"o":{"a":0,"k":100,"ix":3},"x":{"a":0,"k":0,"ix":4},"nm":"Mask 1"}],"ip":0,"op":90,"st":0,"bm":0},{"ddd":0,"ind":10,"ty":2,"nm":"Face + Beard","refId":"image_19","sr":1,"ks":{"o":{"a":0,"k":100,"ix":11},"r":{"a":1,"k":[{"i":{"x":[0.833],"y":[1]},"o":{"x":[0.333],"y":[0]},"n":["0p833_1_0p333_0"],"t":30,"s":[0],"e":[6.527]},{"i":{"x":[0.833],"y":[1]},"o":{"x":[0.167],"y":[0]},"n":["0p833_1_0p167_0"],"t":40,"s":[6.527],"e":[6.527]},{"i":{"x":[0.667],"y":[1]},"o":{"x":[0.167],"y":[0]},"n":["0p667_1_0p167_0"],"t":42,"s":[6.527],"e":[0]},{"i":{"x":[0.833],"y":[1]},"o":{"x":[0.333],"y":[0]},"n":["0p833_1_0p333_0"],"t":50,"s":[0],"e":[-9.789]},{"i":{"x":[0.833],"y":[1]},"o":{"x":[0.167],"y":[0]},"n":["0p833_1_0p167_0"],"t":60,"s":[-9.789],"e":[-9.789]},{"i":{"x":[0.667],"y":[1]},"o":{"x":[0.167],"y":[0]},"n":["0p667_1_0p167_0"],"t":62,"s":[-9.789],"e":[0]},{"t":70}],"ix":10},"p":{"a":1,"k":[{"i":{"x":0.667,"y":1},"o":{"x":0.333,"y":0},"n":"0p667_1_0p333_0","t":30,"s":[220,310.5,0],"e":[233,313.5,0],"to":[2.16666674613953,0.5,0],"ti":[-2.16666674613953,-0.5,0]},{"i":{"x":0.667,"y":0.667},"o":{"x":0.333,"y":0.333},"n":"0p667_0p667_0p333_0p333","t":40,"s":[233,313.5,0],"e":[233,313.5,0],"to":[0,0,0],"ti":[0,0,0]},{"i":{"x":0.667,"y":1},"o":{"x":0.333,"y":0},"n":"0p667_1_0p333_0","t":42,"s":[233,313.5,0],"e":[220,310.5,0],"to":[-2.16666674613953,-0.5,0],"ti":[5.66666650772095,-0.16666667163372,0]},{"i":{"x":0.667,"y":1},"o":{"x":0.333,"y":0},"n":"0p667_1_0p333_0","t":50,"s":[220,310.5,0],"e":[199,314.5,0],"to":[-5.66666650772095,0.16666667163372,0],"ti":[3.5,-0.66666668653488,0]},{"i":{"x":0.667,"y":0.667},"o":{"x":0.333,"y":0.333},"n":"0p667_0p667_0p333_0p333","t":60,"s":[199,314.5,0],"e":[199,314.5,0],"to":[0,0,0],"ti":[0,0,0]},{"i":{"x":0.667,"y":1},"o":{"x":0.333,"y":0},"n":"0p667_1_0p333_0","t":62,"s":[199,314.5,0],"e":[220,310.5,0],"to":[3.5,-0.66666668653488,0],"ti":[-3.5,0.66666668653488,0]},{"t":70}],"ix":2},"a":{"a":0,"k":[220,310.5,0],"ix":1},"s":{"a":1,"k":[{"i":{"x":[0.667,0.667,0.667],"y":[1,1,1]},"o":{"x":[0.333,0.333,0.333],"y":[0,0,0]},"n":["0p667_1_0p333_0","0p667_1_0p333_0","0p667_1_0p333_0"],"t":30,"s":[77.456,77.456,100],"e":[77.456,77.456,100]},{"i":{"x":[0.667,0.667,0.667],"y":[1,1,1]},"o":{"x":[0.333,0.333,0.333],"y":[0,0,0]},"n":["0p667_1_0p333_0","0p667_1_0p333_0","0p667_1_0p333_0"],"t":50,"s":[77.456,77.456,100],"e":[77.456,77.456,100]},{"t":70}],"ix":6}},"ao":0,"hasMask":true,"masksProperties":[{"inv":false,"mode":"a","pt":{"a":0,"k":{"i":[[0,-92.172],[0,0],[-92.047,0],[0,0],[0,92.172],[0,0],[92.047,0],[0,0]],"o":[[0,0],[0,92.172],[0,0],[92.047,0],[0,0],[0,-92.172],[0,0],[-92.047,0]],"v":[[34,176.892],[34,337.108],[200.667,504],[237.333,504],[404,337.108],[404,176.892],[237.333,10],[200.667,10]],"c":true},"ix":1},"o":{"a":0,"k":100,"ix":3},"x":{"a":0,"k":0,"ix":4},"nm":"Mask 1"}],"ip":0,"op":90,"st":0,"bm":0},{"ddd":0,"ind":11,"ty":0,"nm":"Ears","refId":"comp_5","sr":1,"ks":{"o":{"a":0,"k":100,"ix":11},"r":{"a":1,"k":[{"i":{"x":[0.833],"y":[1]},"o":{"x":[0.333],"y":[0]},"n":["0p833_1_0p333_0"],"t":30,"s":[0],"e":[6.527]},{"i":{"x":[0.833],"y":[1]},"o":{"x":[0.167],"y":[0]},"n":["0p833_1_0p167_0"],"t":40,"s":[6.527],"e":[6.527]},{"i":{"x":[0.667],"y":[1]},"o":{"x":[0.167],"y":[0]},"n":["0p667_1_0p167_0"],"t":42,"s":[6.527],"e":[0]},{"i":{"x":[0.833],"y":[1]},"o":{"x":[0.333],"y":[0]},"n":["0p833_1_0p333_0"],"t":50,"s":[0],"e":[-9.789]},{"i":{"x":[0.833],"y":[1]},"o":{"x":[0.167],"y":[0]},"n":["0p833_1_0p167_0"],"t":60,"s":[-9.789],"e":[-9.789]},{"i":{"x":[0.667],"y":[1]},"o":{"x":[0.167],"y":[0]},"n":["0p667_1_0p167_0"],"t":62,"s":[-9.789],"e":[0]},{"t":70}],"ix":10},"p":{"a":1,"k":[{"i":{"x":0.667,"y":1},"o":{"x":0.333,"y":0},"n":"0p667_1_0p333_0","t":30,"s":[220,310.5,0],"e":[234,307.5,0],"to":[2.33333325386047,-0.5,0],"ti":[-2.33333325386047,0.5,0]},{"i":{"x":0.667,"y":0.667},"o":{"x":0.333,"y":0.333},"n":"0p667_0p667_0p333_0p333","t":40,"s":[234,307.5,0],"e":[234,307.5,0],"to":[0,0,0],"ti":[0,0,0]},{"i":{"x":0.667,"y":1},"o":{"x":0.333,"y":0},"n":"0p667_1_0p333_0","t":42,"s":[234,307.5,0],"e":[220,310.5,0],"to":[-2.33333325386047,0.5,0],"ti":[6.16666650772095,-0.5,0]},{"i":{"x":0.667,"y":1},"o":{"x":0.333,"y":0},"n":"0p667_1_0p333_0","t":50,"s":[220,310.5,0],"e":[197,310.5,0],"to":[-6.16666650772095,0.5,0],"ti":[3.83333325386047,0,0]},{"i":{"x":0.667,"y":0.667},"o":{"x":0.333,"y":0.333},"n":"0p667_0p667_0p333_0p333","t":60,"s":[197,310.5,0],"e":[197,310.5,0],"to":[0,0,0],"ti":[0,0,0]},{"i":{"x":0.667,"y":1},"o":{"x":0.333,"y":0},"n":"0p667_1_0p333_0","t":62,"s":[197,310.5,0],"e":[220,310.5,0],"to":[3.83333325386047,0,0],"ti":[-3.83333325386047,0,0]},{"t":70}],"ix":2},"a":{"a":0,"k":[220,310.5,0],"ix":1},"s":{"a":1,"k":[{"i":{"x":[0.667,0.667,0.667],"y":[1,1,1]},"o":{"x":[0.333,0.333,0.333],"y":[0,0,0]},"n":["0p667_1_0p333_0","0p667_1_0p333_0","0p667_1_0p333_0"],"t":30,"s":[77.456,77.456,100],"e":[77.456,77.456,100]},{"i":{"x":[0.667,0.667,0.667],"y":[1,1,1]},"o":{"x":[0.333,0.333,0.333],"y":[0,0,0]},"n":["0p667_1_0p333_0","0p667_1_0p333_0","0p667_1_0p333_0"],"t":50,"s":[77.456,77.456,100],"e":[77.456,77.456,100]},{"t":70}],"ix":6}},"ao":0,"w":440,"h":621,"ip":0,"op":900,"st":0,"bm":0},{"ddd":0,"ind":12,"ty":2,"nm":"Neck","refId":"image_24","sr":1,"ks":{"o":{"a":0,"k":100,"ix":11},"r":{"a":0,"k":0,"ix":10},"p":{"a":0,"k":[220,310.5,0],"ix":2},"a":{"a":0,"k":[220,310.5,0],"ix":1},"s":{"a":0,"k":[77.456,77.456,100],"ix":6}},"ao":0,"hasMask":true,"masksProperties":[{"inv":false,"mode":"a","pt":{"a":0,"k":{"i":[[-17.143,0],[0,0],[0,-17.143],[0,0],[17.143,0],[0,0],[0,17.143],[0,0]],"o":[[0,0],[17.143,0],[0,0],[0,17.143],[0,0],[-17.143,0],[0,0],[0,-17.143]],"v":[[201,481],[239,481],[270,512],[270,512],[239,543],[201,543],[170,512],[170,512]],"c":true},"ix":1},"o":{"a":0,"k":100,"ix":3},"x":{"a":0,"k":0,"ix":4},"nm":"Mask 1"}],"ip":0,"op":90,"st":0,"bm":0},{"ddd":0,"ind":13,"ty":2,"nm":"Body","refId":"image_25","sr":1,"ks":{"o":{"a":0,"k":100,"ix":11},"r":{"a":0,"k":0,"ix":10},"p":{"a":0,"k":[220,310.5,0],"ix":2},"a":{"a":0,"k":[220,310.5,0],"ix":1},"s":{"a":0,"k":[77.456,77.456,100],"ix":6}},"ao":0,"hasMask":true,"masksProperties":[{"inv":false,"mode":"a","pt":{"a":0,"k":{"i":[[0,30.652],[-77.32,0],[0,-30.652],[77.32,0]],"o":[[0,-30.652],[77.32,0],[0,30.652],[-77.32,0]],"v":[[80,565.5],[220,510],[360,565.5],[220,621]],"c":true},"ix":1},"o":{"a":0,"k":100,"ix":3},"x":{"a":0,"k":0,"ix":4},"nm":"Mask 1"}],"ip":0,"op":90,"st":0,"bm":0}],"markers":[]}